ahegao/__init__.py
ahegao/__version__.py
ahegao/api.py
ahegao/exceptions.py
ahegao-1.0.1.dist-info/LICENSE
ahegao-1.0.1.dist-info/METADATA
ahegao-1.0.1.dist-info/WHEEL
ahegao-1.0.1.dist-info/top_level.txt
ahegao-1.0.1.dist-info/RECORD
