Metadata-Version: 2.1
Name: ahegao
Version: 1.0.1
Summary: Ahegao API wrapper
Home-page: https://github.com/AhegaoTeam/AhegaoAPI
Author: SantaSpeen
Author-email: admin@ahegao.ovh
License: MIT
Project-URL: Documentation, https://docs.ahegao.dev/
Project-URL: Source, https://github.com/AhegaoTeam/AhegaoAPIPython
Platform: UNKNOWN
Classifier: Programming Language :: Python :: 3
Classifier: License :: OSI Approved :: MIT License
Classifier: Operating System :: OS Independent
Requires-Python: >=3.6
License-File: LICENSE
Requires-Dist: requests
